pyproject_installer/__init__.py
pyproject_installer/__main__.py
pyproject_installer/codes.py
pyproject_installer/errors.py
pyproject_installer/version.py
pyproject_installer/_vendor/__init__.py
pyproject_installer/_vendor/packaging/__init__.py
pyproject_installer/_vendor/packaging/_elffile.py
pyproject_installer/_vendor/packaging/_manylinux.py
pyproject_installer/_vendor/packaging/_musllinux.py
pyproject_installer/_vendor/packaging/_parser.py
pyproject_installer/_vendor/packaging/_structures.py
pyproject_installer/_vendor/packaging/_tokenizer.py
pyproject_installer/_vendor/packaging/markers.py
pyproject_installer/_vendor/packaging/metadata.py
pyproject_installer/_vendor/packaging/requirements.py
pyproject_installer/_vendor/packaging/specifiers.py
pyproject_installer/_vendor/packaging/tags.py
pyproject_installer/_vendor/packaging/utils.py
pyproject_installer/_vendor/packaging/version.py
pyproject_installer/_vendor/packaging/licenses/__init__.py
pyproject_installer/_vendor/packaging/licenses/_spdx.py
pyproject_installer/_vendor/tomli/__init__.py
pyproject_installer/_vendor/tomli/_parser.py
pyproject_installer/_vendor/tomli/_re.py
pyproject_installer/_vendor/tomli/_types.py
pyproject_installer/build_cmd/__init__.py
pyproject_installer/build_cmd/_build.py
pyproject_installer/deps_cmd/__init__.py
pyproject_installer/deps_cmd/_deps_command.py
pyproject_installer/deps_cmd/deps_config.py
pyproject_installer/deps_cmd/collectors/__init__.py
pyproject_installer/deps_cmd/collectors/collector.py
pyproject_installer/deps_cmd/collectors/hatch.py
pyproject_installer/deps_cmd/collectors/metadata.py
pyproject_installer/deps_cmd/collectors/pdm.py
pyproject_installer/deps_cmd/collectors/pep517.py
pyproject_installer/deps_cmd/collectors/pep518.py
pyproject_installer/deps_cmd/collectors/pep735.py
pyproject_installer/deps_cmd/collectors/pip_reqfile.py
pyproject_installer/deps_cmd/collectors/pipenv.py
pyproject_installer/deps_cmd/collectors/poetry.py
pyproject_installer-0.5.6.dist-info/WHEEL
pyproject_installer-0.5.6.dist-info/METADATA
pyproject_installer-0.5.6.dist-info/LICENSE
pyproject_installer-0.5.6.dist-info/RECORD
