Metadata-Version: 2.1
Name: pyproject-installer
Version: 0.5.6
Summary: Pyproject installer
Author-email: Stanislav Levin <slev@altlinux.org>
License: MIT
Project-URL: source,https://github.com/stanislavlevin/pyproject_installer
Project-URL: tracker,https://github.com/stanislavlevin/pyproject_installer/issues
Keywords: packaging,PEP517,build,install
Classifier: Development Status :: 4 - Beta
Classifier: Intended Audience :: Developers
Classifier: License :: OSI Approved :: MIT License
Classifier: Operating System :: Unix
Classifier: Programming Language :: Python :: 3
Classifier: Programming Language :: Python :: 3 :: Only
Classifier: Programming Language :: Python :: 3.9
Classifier: Programming Language :: Python :: 3.10
Classifier: Programming Language :: Python :: 3.11
Classifier: Programming Language :: Python :: 3.12
Classifier: Programming Language :: Python :: 3.13
Classifier: Programming Language :: Python :: 3.14
Classifier: Topic :: Software Development :: Libraries
Requires-Python: >=3.9
